pysimpletimers/__init__.py
pysimpletimers/timer.py
pysimpletimers-0.0.4.dist-info/LICENSE
pysimpletimers-0.0.4.dist-info/METADATA
pysimpletimers-0.0.4.dist-info/WHEEL
pysimpletimers-0.0.4.dist-info/top_level.txt
pysimpletimers-0.0.4.dist-info/RECORD
