Metadata-Version: 2.1
Name: pysimpletimers
Version: 0.0.4
Summary: A small module that lets you easily create timers that will run a callback function when a certain amount of time has been waited.
Author-email: Ilunawoo <author@example.com>
License: MIT License        
Project-URL: Homepage, https://github.com/Ilunawoo/pySimpleTimers
Project-URL: Bug Tracker, https://github.com/Ilunawoo/pySimpleTimers/issues
Classifier: Programming Language :: Python :: 3
Classifier: License :: OSI Approved :: MIT License
Classifier: Operating System :: OS Independent
Requires-Python: >=3.4
License-File: LICENSE
